Ej. 4/Ej4.v
module BF3(input wire ENABLE, input wire [3:0]IN, output wire [3:0]OUT);
	assign OUT = ENABLE ? IN : 4'bz;
endmodule

Ej. 4/Ej4_tb.v
module Ej4();
  reg [3:0]IN; reg ENABLE; 
  wire [3:0]OUT; 
	BF3 U4(IN, ENABLE, OUT);

  initial begin
	#5
    $display("\n");
	$display("Ejercicio 4");
    $display("Ej4 IN | OUT");
    $display("-----------------");
    $monitor("%b %b | %b", ENABLE, IN, OUT);
       ENABLE = 0; IN = 1;
    #1 ENABLE = 1;
	#10 ENABLE = 0;
	#5 IN = 5;
	#5 IN = 15;
	#5 ENABLE = 1;
	#5 IN = 3;
	#5 IN = 6;
	#5 ENABLE = 0;

  end
	initial
    #50 $finish;
  initial begin
    $dumpfile("Ej4_tb.vcd");
    $dumpvars(0, Ej4);
  end
endmodule

Ej. 4/Ej4_tb.vcd
$date
	Fri Oct 30 19:14:04 2020
$end
$version
	Icarus Verilog
$end
$timescale
	1ps
$end
$scope module Ej4 $end
$var wire 4 ! OUT [3:0] $end
$var reg 1 " ENABLE $end
$var reg 4 # IN [3:0] $end
$scope module U4 $end
$var wire 1 $ ENABLE $end
$var wire 4 % IN [3:0] $end
$var wire 4 & OUT [3:0] $end
$upscope $end
$upscope $end
$enddefinitions $end
#0
$dumpvars
bx &
b0x %
x$
bx #
x"
bx !
$end
#5
b0 !
b0 &
1$
b1 #
b0 %
0"
#6
b1 !
b1 &
b1 %
1"
#16
b0 !
b0 &
b0 %
0"
#21
b101 #
#26
b1111 #
#31
b1 !
b1 &
b1 %
1"
#36
b11 #
#41
bz !
bz &
0$
b110 #
#46
b0 %
0"
