Ej. 1/Ej1.v
module FD1(input wire CLOCK, input wire D, input wire RESET, input wire ENABLE, output Q);
reg Q;
	always @(posedge CLOCK or	posedge RESET)
		if (RESET)begin
		Q <= 0;
	end else if(ENABLE) begin
		Q <= D;
	end
endmodule


module FD2 (input wire CLOCK, input wire [1:0]D, input wire RESET, input wire ENABLE, output wire [1:0]Q);
	FD1 O0(CLOCK, D[0], RESET, ENABLE, Q[0]);
	FD1 O1(CLOCK, D[1], RESET, ENABLE, Q[1]);
endmodule


//Modulo FlipFlopD de 4 bitsx
module FlipD4 (input wire CLOCK, input wire [3:0]D, input wire RESET, input wire ENABLE, output wire [3:0]Q);
	FD2 O3(CLOCK, D[1:0], RESET, ENABLE, Q[1:0]);
	FD2 O4(CLOCK, D[3:2], RESET, ENABLE, Q[3:2]);
endmodule

Ej. 1/Ej1_tb.v
module Ej_1();

  reg CLOCK, RESET, D1, ENABLE; reg [1:0]D2; reg [3:0]D4; 
  wire Q1; wire [1:0]Q2; wire [3:0]Q4;

	FD1 U1(CLOCK, D1, RESET, ENABLE, Q1);
	FD2 U2(CLOCK, D2, RESET, ENABLE, Q2);
	FlipD4 U3(CLOCK, D4, RESET, ENABLE, Q4);

initial begin
	CLOCK=0;
	forever #5 CLOCK = ~CLOCK;
end
  initial begin
	#5
	$display("Ej1, FlipFlop D 1 b");
    $display("CLOCK E D | Q");
    $display("------------");
    $monitor("%b   %b %b | %b", CLOCK, ENABLE, D1, Q1);
       RESET = 1; D1 = 1; ENABLE = 0;
    #1 RESET = 0;
	#10 D1 = 1;
	#10 ENABLE = 1;
	#15 D1 = 0;
  end

  initial begin
	#60
	$display("Ej1, FlipFlop D 2 b");
    $display("CLOCK E  D | Q");
    $display("-------------");
    $monitor("%b   %b %b |%b", CLOCK, ENABLE, D2, Q2);
       RESET = 1; D2 = 1;
    #1 RESET = 0;
	#5 ENABLE = 1;
	#10 D2 = 2;
	#10 D2 = 3;
  end
 
  initial begin
	#100
    $display("\n");
	$display("Ej1, FlipFlop D 4 b");
    $display("CLOCK E  D   |  Q");
    $display("-----------------");
    $monitor("%b   %b %b | %b", CLOCK, ENABLE, D4, Q4);
       RESET = 1; D4 = 1;
    #1 RESET = 0;
	#5 ENABLE = 1;
	#10 D4 = 2;
	#10 D4 = 3;
	#10 D4 = 10;
  end


	initial
    #150 $finish;
  initial begin
    $dumpfile("Ej1_tb.vcd");
    $dumpvars(0, Ej_1);
  end
endmodule

Ej. 1/Ej1_tb.vcd
$date
	Fri Oct 30 19:20:28 2020
$end
$version
	Icarus Verilog
$end
$timescale
	1ps
$end
$scope module Ej_1 $end
$var wire 4 ! Q4 [3:0] $end
$var wire 2 " Q2 [1:0] $end
$var wire 1 # Q1 $end
$var reg 1 $ CLOCK $end
$var reg 1 % D1 $end
$var reg 2 & D2 [1:0] $end
$var reg 4 ' D4 [3:0] $end
$var reg 1 ( ENABLE $end
$var reg 1 ) RESET $end
$scope module U1 $end
$var wire 1 $ CLOCK $end
$var wire 1 % D $end
$var wire 1 ( ENABLE $end
$var wire 1 ) RESET $end
$var reg 1 # Q $end
$upscope $end
$scope module U2 $end
$var wire 1 $ CLOCK $end
$var wire 2 * D [1:0] $end
$var wire 1 ( ENABLE $end
$var wire 1 ) RESET $end
$var wire 2 + Q [1:0] $end
$scope module O0 $end
$var wire 1 $ CLOCK $end
$var wire 1 , D $end
$var wire 1 ( ENABLE $end
$var wire 1 ) RESET $end
$var reg 1 - Q $end
$upscope $end
$scope module O1 $end
$var wire 1 $ CLOCK $end
$var wire 1 . D $end
$var wire 1 ( ENABLE $end
$var wire 1 ) RESET $end
$var reg 1 / Q $end
$upscope $end
$upscope $end
$scope module U3 $end
$var wire 1 $ CLOCK $end
$var wire 4 0 D [3:0] $end
$var wire 1 ( ENABLE $end
$var wire 1 ) RESET $end
$var wire 4 1 Q [3:0] $end
$scope module O3 $end
$var wire 1 $ CLOCK $end
$var wire 2 2 D [1:0] $end
$var wire 1 ( ENABLE $end
$var wire 1 ) RESET $end
$var wire 2 3 Q [1:0] $end
$scope module O0 $end
$var wire 1 $ CLOCK $end
$var wire 1 4 D $end
$var wire 1 ( ENABLE $end
$var wire 1 ) RESET $end
$var reg 1 5 Q $end
$upscope $end
$scope module O1 $end
$var wire 1 $ CLOCK $end
$var wire 1 6 D $end
$var wire 1 ( ENABLE $end
$var wire 1 ) RESET $end
$var reg 1 7 Q $end
$upscope $end
$upscope $end
$scope module O4 $end
$var wire 1 $ CLOCK $end
$var wire 2 8 D [1:0] $end
$var wire 1 ( ENABLE $end
$var wire 1 ) RESET $end
$var wire 2 9 Q [1:0] $end
$scope module O0 $end
$var wire 1 $ CLOCK $end
$var wire 1 : D $end
$var wire 1 ( ENABLE $end
$var wire 1 ) RESET $end
$var reg 1 ; Q $end
$upscope $end
$scope module O1 $end
$var wire 1 $ CLOCK $end
$var wire 1 < D $end
$var wire 1 ( ENABLE $end
$var wire 1 ) RESET $end
$var reg 1 = Q $end
$upscope $end
$upscope $end
$upscope $end
$upscope $end
$enddefinitions $end
#0
$dumpvars
x=
x<
x;
x:
bx 9
bx 8
x7
x6
x5
x4
bx 3
bx 2
bx 1
bx 0
x/
x.
x-
x,
bx +
bx *
x)
x(
bx '
bx &
x%
0$
x#
bx "
bx !
$end
#5
0#
0-
b0 "
b0 +
0/
05
b0 3
07
0;
b0 !
b0 1
b0 9
0=
0(
1%
1)
1$
#6
0)
#10
0$
#15
1$
#20
0$
#25
1$
#26
1(
#30
0$
#35
x=
bx 9
x;
x7
bx !
bx 1
bx 3
x5
x/
bx "
bx +
x-
1#
1$
#40
0$
#41
0%
#45
0#
1$
#50
0$
#55
1$
#60
0-
b0 "
b0 +
0/
05
b0 3
07
0;
b0 !
b0 1
b0 9
0=
1,
0.
0$
b1 &
b1 *
1)
#61
0)
#65
x=
bx 9
x;
x7
bx !
bx 1
bx 3
x5
b1 "
b1 +
1-
1$
#70
0$
#75
1$
#76
0,
1.
b10 &
b10 *
#80
0$
#85
1/
b10 "
b10 +
0-
1$
#86
1,
b11 &
b11 *
#90
0$
#95
b11 "
b11 +
1-
1$
#100
0=
b0 9
0;
07
b0 !
b0 1
b0 3
05
0/
b0 "
b0 +
0-
14
06
0:
0<
b1 2
b0 8
0$
b1 '
b1 0
1)
#101
0)
#105
1-
b11 "
b11 +
1/
b1 !
b1 1
b1 3
15
1$
#110
0$
#115
1$
#116
04
16
b10 2
b10 '
b10 0
#120
0$
#125
05
b10 !
b10 1
b10 3
17
1$
#126
14
b11 2
b11 '
b11 0
#130
0$
#135
b11 !
b11 1
b11 3
15
1$
#136
04
1<
b10 2
b10 8
b1010 '
b1010 0
#140
0$
#145
b10 3
05
b1010 !
b1010 1
b10 9
1=
1$
