Ej. 3/Ej3.v
module FD1(input wire CLOCK, input wire FD, input wire RESET, input wire ENABLE, output Q);
reg Q;
	always @(posedge CLOCK or	posedge RESET or posedge ENABLE)
		if (RESET)begin
		Q <= 0;
	end else if(ENABLE) begin
		Q <= FD;
	end
endmodule

module FlipJK(input wire CLOCK, RESET, ENABLE, J, K, output wire Q);
	FD1 O5(CLOCK, ~K&Q | J&~Q, RESET, ENABLE, Q);
endmodule

Ej. 3/Ej3_tb.v
module Ej3();

  reg CLOCK, RESET, enable, K, J; 
  wire QJK; 
	FlipJK U4(CLOCK, RESET, enable, J, K, QJK);

initial begin
	CLOCK=0;
	forever #5 CLOCK = ~CLOCK;
end

  initial begin
	#5
	$display("Ej3");
    $display("CLOCK J K |  Q");
    $display("-----------------");
    $monitor("%b   %b %b | %b", CLOCK, J, K, QJK);
       RESET = 1; enable = 0; J = 0; K = 0;
    #1 RESET = 0; enable = 1;
	#10 J = 1;
	#15 J = 0; K = 1;
	#15 J = 1;

  end

	initial
    #70 $finish;
  initial begin
    $dumpfile("Ej_tb.vcd");
    $dumpvars(0, Ej3);
  end
endmodule

Ej. 3/Ej_tb.vcd
$date
	Fri Oct 30 19:07:52 2020
$end
$version
	Icarus Verilog
$end
$timescale
	1ps
$end
$scope module Ej3 $end
$var wire 1 ! QJK $end
$var reg 1 " CLOCK $end
$var reg 1 # J $end
$var reg 1 $ K $end
$var reg 1 % RESET $end
$var reg 1 & enable $end
$scope module U4 $end
$var wire 1 " CLOCK $end
$var wire 1 & ENABLE $end
$var wire 1 # J $end
$var wire 1 $ K $end
$var wire 1 % RESET $end
$var wire 1 ! Q $end
$scope module O5 $end
$var wire 1 " CLOCK $end
$var wire 1 & ENABLE $end
$var wire 1 ' FD $end
$var wire 1 % RESET $end
$var reg 1 ! Q $end
$upscope $end
$upscope $end
$upscope $end
$enddefinitions $end
#0
$dumpvars
x'
x&
x%
x$
x#
0"
x!
$end
#5
0'
0!
0$
0#
0&
1%
1"
#6
1&
0%
#10
0"
#15
1"
#16
1'
1#
#20
0"
#25
1!
1"
#30
0"
#31
0'
1$
0#
#35
0!
1"
#40
0"
#45
1"
#46
1'
1#
#50
0"
#55
0'
1!
1"
#60
0"
#65
1'
0!
1"
