Ej. 2/Ej2.v

module FD1(input wire CLOCK, input wire FFD, input wire RESET, input wire ENABLE, output Q);
reg Q;
	always @(posedge CLOCK or	posedge RESET)
		if (RESET)begin
		Q <= 0;
	end else if(ENABLE) begin
		Q <= FFD;
	end
endmodule


module FlipT(input wire CLOCK, RESET, ENABLE, output wire Q);
	FD1 O5(CLOCK, ~Q, RESET, ENABLE, Q);
endmodule

Ej. 2/Ej2_tb.v
module Ej2();
  reg CLOCK, RESET, ENABLE; 
  wire QT; 
	FlipT Y4(CLOCK, RESET, ENABLE, QT);


initial begin
	CLOCK=0;
	forever #1 CLOCK = ~CLOCK;
end

  initial begin
	#5
	$display("Ej2");
    $display("CLOCK Enable Reset |  Q");
    $display("-----------------");
    $monitor("%b   %b %b | %b", CLOCK, ENABLE, RESET, QT);
       RESET = 1; ENABLE = 0;
    #1 RESET = 0; ENABLE = 1;

  end

	initial
    #15 $finish;
  initial begin
    $dumpfile("ej2_tb.vcd");
    $dumpvars(0, Ej2);
  end
endmodule

Ej. 2/ej2_tb.vcd
$date
	Fri Oct 30 18:37:54 2020
$end
$version
	Icarus Verilog
$end
$timescale
	1ps
$end
$scope module Ej2 $end
$var wire 1 ! QT $end
$var reg 1 " CLOCK $end
$var reg 1 # ENABLE $end
$var reg 1 $ RESET $end
$scope module Y4 $end
$var wire 1 " CLOCK $end
$var wire 1 # ENABLE $end
$var wire 1 $ RESET $end
$var wire 1 ! Q $end
$scope module O5 $end
$var wire 1 " CLOCK $end
$var wire 1 # ENABLE $end
$var wire 1 % FFD $end
$var wire 1 $ RESET $end
$var reg 1 ! Q $end
$upscope $end
$upscope $end
$upscope $end
$enddefinitions $end
#0
$dumpvars
x%
x$
x#
0"
x!
$end
#1
1"
#2
0"
#3
1"
#4
0"
#5
1%
0!
1"
0#
1$
#6
0"
1#
0$
#7
0%
1!
1"
#8
0"
#9
1%
0!
1"
#10
0"
#11
0%
1!
1"
#12
0"
#13
1%
0!
1"
#14
0"
#15
0%
1!
1"
